odoo/addons/agreement_project/README.rst
odoo/addons/agreement_project/__init__.py
odoo/addons/agreement_project/__manifest__.py
odoo/addons/agreement_project/i18n/agreement_project.pot
odoo/addons/agreement_project/i18n/de.po
odoo/addons/agreement_project/i18n/fr.po
odoo/addons/agreement_project/models/__init__.py
odoo/addons/agreement_project/models/agreement.py
odoo/addons/agreement_project/models/project.py
odoo/addons/agreement_project/readme/CONTRIBUTORS.rst
odoo/addons/agreement_project/readme/CREDITS.rst
odoo/addons/agreement_project/readme/DESCRIPTION.rst
odoo/addons/agreement_project/readme/ROADMAP.rst
odoo/addons/agreement_project/readme/USAGE.rst
odoo/addons/agreement_project/static/description/icon.png
odoo/addons/agreement_project/static/description/index.html
odoo/addons/agreement_project/views/agreement_view.xml
odoo/addons/agreement_project/views/project_view.xml
odoo11_addon_agreement_project-11.0.0.0.1.99.dev10.dist-info/METADATA
odoo11_addon_agreement_project-11.0.0.0.1.99.dev10.dist-info/WHEEL
odoo11_addon_agreement_project-11.0.0.0.1.99.dev10.dist-info/top_level.txt
odoo11_addon_agreement_project-11.0.0.0.1.99.dev10.dist-info/RECORD
